tdg/__init__.py
tdg/client.py
tdg_sdk-0.1.0.dist-info/METADATA
tdg_sdk-0.1.0.dist-info/WHEEL
tdg_sdk-0.1.0.dist-info/top_level.txt
tdg_sdk-0.1.0.dist-info/RECORD
